src/mermaidmd2pdf/__init__.py
src/mermaidmd2pdf/cli.py
src/mermaidmd2pdf/dependencies.py
src/mermaidmd2pdf/generator.py
src/mermaidmd2pdf/pdf.py
src/mermaidmd2pdf/processor.py
src/mermaidmd2pdf/validator.py
mermaidmd2pdf-0.1.0.dist-info/METADATA
mermaidmd2pdf-0.1.0.dist-info/WHEEL
mermaidmd2pdf-0.1.0.dist-info/entry_points.txt
mermaidmd2pdf-0.1.0.dist-info/licenses/LICENSE
mermaidmd2pdf-0.1.0.dist-info/RECORD
