Metadata-Version: 2.4
Name: mermaidmd2pdf
Version: 0.1.0
Summary: Convert Markdown files with Mermaid diagrams to PDF
Project-URL: Homepage, https://github.com/yourusername/MermaidMD2PDF
Project-URL: Documentation, https://github.com/yourusername/MermaidMD2PDF#readme
Project-URL: Repository, https://github.com/yourusername/MermaidMD2PDF.git
Project-URL: Issues, https://github.com/yourusername/MermaidMD2PDF/issues
Author-email: Chad Walters <chad@example.com>
License-Expression: MIT
License-File: LICENSE
Keywords: converter,diagrams,documentation,markdown,mermaid,pdf
Classifier: Development Status :: 3 - Alpha
Classifier: Intended Audience :: Developers
Classifier: License :: OSI Approved :: MIT License
Classifier: Programming Language :: Python :: 3
Classifier: Programming Language :: Python :: 3.8
Classifier: Programming Language :: Python :: 3.9
Classifier: Programming Language :: Python :: 3.10
Classifier: Programming Language :: Python :: 3.11
Classifier: Topic :: Documentation
Classifier: Topic :: Software Development :: Documentation
Classifier: Topic :: Text Processing :: Markup :: Markdown
Requires-Python: >=3.8
Requires-Dist: click>=8.0.0
Requires-Dist: markdown>=3.5.0
Requires-Dist: packaging>=23.2
Requires-Dist: weasyprint>=60.2
Provides-Extra: dev
Requires-Dist: black>=24.0.0; extra == 'dev'
Requires-Dist: isort>=5.13.0; extra == 'dev'
Requires-Dist: mypy>=1.8.0; extra == 'dev'
Requires-Dist: psutil>=5.9.0; extra == 'dev'
Requires-Dist: pytest-cov>=4.1.0; extra == 'dev'
Requires-Dist: pytest>=8.0.0; extra == 'dev'
Requires-Dist: ruff>=0.2.0; extra == 'dev'
